[
  {
    "fileInfo": {
      "id": 220,
      "name": "bbbbbb",
      "extName": "mp-page"
    },
    "fileData": {},
    "text": "首页",
    "selectedIconPath": "https://ali-ec.static.yximgs.com/udata/pkg/eshop/chrome-plugin-upload/2023-03-15/1678869092382.c95d52033e4fb365.png",
    "selectedIconStyle": {
      "width": "32px",
      "height": "32px"
    },
    "selectedTextStyle": {
      "lineHeight": "14px",
      "letterSpacing": "0px",
      "fontSize": "14px",
      "fontWeight": 400,
      "color": "#222222",
      "fontStyle": "normal",
      "fontFamily": "",
      "styleEditorUnfold": true
    },
    "normalIconPath": "https://ali-ec.static.yximgs.com/udata/pkg/eshop/chrome-plugin-upload/2023-03-15/1678869110750.f5cf009cd90a320b.png",
    "normalIconStyle": {
      "width": "32px",
      "height": "32px"
    },
    "normalTextStyle": {
      "lineHeight": "14px",
      "letterSpacing": "0px",
      "fontSize": "14px",
      "fontWeight": 400,
      "color": "#222222",
      "fontStyle": "normal",
      "fontFamily": "",
      "styleEditorUnfold": true
    },
    "fileToJson": {
      "content": {
        "xg.desn.stageview": {
          "D": {
            "C": [
              "xg.desn.sdk.ModelState",
              "xg.desn.designer.stageview.ViewSlotModel",
              "xg.desn.designer.stageview.geo.SlotStyleModel",
              "xg.desn.sdk.ComStyle",
              "xg.desn.designer.stageview.topl.PinModel",
              "xg.desn.designer.stageview.geo.GeoComModel",
              "xg.desn.sdk.ComRuntimeModel",
              "xg.desn.designer.stageview.topl.ToplComModel",
              "xg.desn.designer.stageview.topl.DiagramModel",
              "xg.desn.designer.stageview.topl.FrameModel",
              "xg.desn.designer.stageview.geo.SlotModel",
              "xg.desn.designer.stageview.geo.GeoViewModel",
              "xg.desn.designer.stageview.topl.ToplViewModel",
              "xg.desn.designer.stageview.StageViewModel"
            ],
            "W": {
              "id": "_0_",
              "state": "_1_",
              "designerVersion": "_2_",
              "pluginDataset": "_3_",
              "envVars": "_4_",
              "_themes": "_5_",
              "viewSlots": "_6_",
              "top": "_7_",
              "closeable": "_8_",
              "status": "_9_",
              "tabs": "_10_",
              "showTitleBar": "_11_",
              "_height": "_12_",
              "height": "_13_",
              "bottom": "_14_",
              "editViewWidth": "_15_",
              "mainModule": "_16_",
              "instId": "_17_",
              "title": "_18_",
              "slot": "_19_",
              "name": "_20_",
              "style": "_21_",
              "zoom": "_22_",
              "layout": "_23_",
              "justifyContent": "_24_",
              "alignItems": "_25_",
              "width": "_26_",
              "left": "_27_",
              "slots": "_28_",
              "comAry": "_29_",
              "init": "_30_",
              "runtime": "_31_",
              "model": "_32_",
              "data": "_33_",
              "items": "_34_",
              "swiperStyle": "_35_",
              "swiperItemStyle": "_36_",
              "inputAry": "_37_",
              "outputAry": "_38_",
              "outputEvents": "_39_",
              "display": "_40_",
              "marginTop": "_41_",
              "marginBottom": "_42_",
              "marginLeft": "_43_",
              "marginRight": "_44_",
              "visibleOnce": "_45_",
              "refId": "_46_",
              "def": "_47_",
              "namespace": "_48_",
              "version": "_49_",
              "_autoRun": "_50_",
              "topl": "_51_",
              "_type": "_52_",
              "foldedStyle": "_53_",
              "configPins": "_54_",
              "_inputPins": "_55_",
              "inputPins": "_56_",
              "zIndex": "_57_",
              "type": "_58_",
              "deletable": "_59_",
              "conAry": "_60_",
              "direction": "_61_",
              "hostId": "_62_",
              "_schema": "_63_",
              "parent": "_64_",
              "schema": "_65_",
              "inputPinsInModel": "_66_",
              "inputPinExts": "_67_",
              "_outputPins": "_68_",
              "outputPins": "_69_",
              "text": "_70_",
              "outputPinsInModel": "_71_",
              "outputPinExts": "_72_",
              "editable": "_73_",
              "isFrame": "_74_",
              "frameAry": "_75_",
              "inputJoints": "_76_",
              "outputJoints": "_77_",
              "ellipsis": "_78_",
              "geo": "_79_",
              "diagramAry": "_80_",
              "commentAry": "_81_",
              "visible": "_82_",
              "_title": "_83_",
              "createTime": "_84_",
              "isGlobal": "_85_",
              "showIO": "_86_",
              "updateTime": "_87_",
              "startFrom": "_88_",
              "focusModelAry": "_89_",
              "zIndexCur": "_90_",
              "con": "_91_",
              "com": "_92_",
              "notes": "_93_",
              "styleInited": "_94_",
              "showType": "_95_",
              "frame": "_96_",
              "frames": "_97_",
              "curDiagram": "_98_"
            }
          },
          "refs": {
            "1": {},
            "3": {},
            "5": {},
            "7": {},
            "10": {},
            "12": {},
            "16": {},
            "18": {},
            "20": {},
            "22": {},
            "24": {},
            "26": {},
            "28": {},
            "30": {},
            "32": {},
            "34": {},
            "36": {},
            "38": {},
            "40": {},
            "44": {},
            "46": {},
            "49": {}
          },
          "def": {
            "_R_": "0"
          }
        }
      },
      "toJson": {
        "-v": "1.0.8",
        "id": "u_EeLha",
        "title": "主场景",
        "deps": [
          {
            "namespace": "mybricks.ktaro.swiper",
            "version": "1.0.0"
          },
          {
            "namespace": "mybricks.ktaro.text",
            "version": "1.0.0"
          }
        ],
        "coms": {
          "u_QFBpa": {
            "def": {
              "namespace": "mybricks.ktaro.swiper",
              "version": "1.0.0"
            },
            "title": "轮播",
            "model": {
              "data": {
                "items": [],
                "swiperStyle": {},
                "swiperItemStyle": {}
              },
              "inputAry": [],
              "outputAry": [],
              "outputEvents": {},
              "style": {
                "display": "block",
                "width": "100%",
                "height": 114,
                "marginTop": 12,
                "marginBottom": 12,
                "marginLeft": 12,
                "marginRight": 12
              }
            },
            "configs": [],
            "inputs": [
              "value",
              "show",
              "hide",
              "showOrHide"
            ],
            "outputs": [
              "onClick"
            ]
          },
          "u_4tDsK": {
            "def": {
              "namespace": "mybricks.ktaro.text",
              "version": "1.0.0"
            },
            "title": "文本",
            "model": {
              "data": {
                "text": "文本内容",
                "style": {},
                "ellipsis": false
              },
              "inputAry": [],
              "outputAry": [],
              "outputEvents": {},
              "style": {
                "display": "block",
                "width": "fit-content"
              }
            },
            "configs": [],
            "inputs": [
              "value",
              "show",
              "hide",
              "showOrHide"
            ],
            "outputs": [
              "onClick"
            ]
          }
        },
        "slot": {
          "id": "u_EeLha",
          "title": "主场景",
          "comAry": [
            {
              "id": "u_QFBpa",
              "def": {
                "namespace": "mybricks.ktaro.swiper",
                "version": "1.0.0"
              }
            },
            {
              "id": "u_4tDsK",
              "def": {
                "namespace": "mybricks.ktaro.text",
                "version": "1.0.0"
              }
            }
          ],
          "style": {
            "zoom": 1,
            "width": 375,
            "height": 667,
            "layout": "flex-column",
            "justifyContent": "flex-start",
            "alignItems": "flex-start"
          }
        },
        "comsAutoRun": {},
        "_inputs": [],
        "_outputs": [],
        "inputs": [],
        "outputs": [],
        "cons": {},
        "pinRels": {},
        "pinProxies": {},
        "plugins": {},
        "configuration": {
          "domainFileMap": {
            "baseFileId": 441
          }
        }
      },
      "pageConfig": {
        "pagePath": "pages/aaa/index"
      }
    }
  },
  {
    "fileInfo": {
      "id": 219,
      "name": "啊啊啊啊啊",
      "extName": "mp-page"
    },
    "fileData": {},
    "text": "我的",
    "selectedIconPath": "https://ali-ec.static.yximgs.com/udata/pkg/eshop/chrome-plugin-upload/2023-03-15/1678869092382.c95d52033e4fb365.png",
    "selectedIconStyle": {
      "width": "32px",
      "height": "32px"
    },
    "selectedTextStyle": {
      "lineHeight": "14px",
      "letterSpacing": "0px",
      "fontSize": "14px",
      "fontWeight": 400,
      "color": "#222222",
      "fontStyle": "normal",
      "fontFamily": "",
      "styleEditorUnfold": true
    },
    "normalIconPath": "https://ali-ec.static.yximgs.com/udata/pkg/eshop/chrome-plugin-upload/2023-03-15/1678869110750.f5cf009cd90a320b.png",
    "normalIconStyle": {
      "width": "32px",
      "height": "32px"
    },
    "normalTextStyle": {
      "lineHeight": "14px",
      "letterSpacing": "0px",
      "fontSize": "14px",
      "fontWeight": 400,
      "color": "#222222",
      "fontStyle": "normal",
      "fontFamily": "",
      "styleEditorUnfold": true
    },
    "fileToJson": {
      "content": {
        "xg.desn.stageview": {
          "D": {
            "C": [
              "xg.desn.sdk.ModelState",
              "xg.desn.designer.stageview.ViewSlotModel",
              "xg.desn.designer.stageview.geo.SlotStyleModel",
              "xg.desn.sdk.ComStyle",
              "xg.desn.designer.stageview.topl.PinModel",
              "xg.desn.designer.stageview.geo.GeoComModel",
              "xg.desn.sdk.ComRuntimeModel",
              "xg.desn.designer.stageview.topl.ToplComModel",
              "xg.desn.designer.stageview.topl.DiagramModel",
              "xg.desn.designer.stageview.topl.FrameModel",
              "xg.desn.designer.stageview.geo.SlotModel",
              "xg.desn.designer.stageview.geo.GeoViewModel",
              "xg.desn.designer.stageview.topl.ToplViewModel",
              "xg.desn.designer.stageview.StageViewModel"
            ],
            "W": {
              "id": "_0_",
              "state": "_1_",
              "designerVersion": "_2_",
              "pluginDataset": "_3_",
              "envVars": "_4_",
              "_themes": "_5_",
              "viewSlots": "_6_",
              "top": "_7_",
              "closeable": "_8_",
              "status": "_9_",
              "tabs": "_10_",
              "showTitleBar": "_11_",
              "_height": "_12_",
              "height": "_13_",
              "bottom": "_14_",
              "editViewWidth": "_15_",
              "mainModule": "_16_",
              "instId": "_17_",
              "title": "_18_",
              "slot": "_19_",
              "name": "_20_",
              "style": "_21_",
              "zoom": "_22_",
              "layout": "_23_",
              "justifyContent": "_24_",
              "alignItems": "_25_",
              "width": "_26_",
              "left": "_27_",
              "slots": "_28_",
              "comAry": "_29_",
              "init": "_30_",
              "runtime": "_31_",
              "model": "_32_",
              "data": "_33_",
              "items": "_34_",
              "swiperStyle": "_35_",
              "swiperItemStyle": "_36_",
              "lineHeight": "_37_",
              "letterSpacing": "_38_",
              "fontSize": "_39_",
              "fontWeight": "_40_",
              "color": "_41_",
              "fontStyle": "_42_",
              "fontFamily": "_43_",
              "styleEditorUnfold": "_44_",
              "inputAry": "_45_",
              "outputAry": "_46_",
              "outputEvents": "_47_",
              "onClick": "_48_",
              "type": "_49_",
              "options": "_50_",
              "active": "_51_",
              "display": "_52_",
              "marginTop": "_53_",
              "marginBottom": "_54_",
              "marginLeft": "_55_",
              "marginRight": "_56_",
              "visibleOnce": "_57_",
              "refId": "_58_",
              "def": "_59_",
              "namespace": "_60_",
              "version": "_61_",
              "_autoRun": "_62_",
              "topl": "_63_",
              "_type": "_64_",
              "foldedStyle": "_65_",
              "configPins": "_66_",
              "_inputPins": "_67_",
              "inputPins": "_68_",
              "zIndex": "_69_",
              "deletable": "_70_",
              "conAry": "_71_",
              "direction": "_72_",
              "hostId": "_73_",
              "_schema": "_74_",
              "parent": "_75_",
              "schema": "_76_",
              "inputPinsInModel": "_77_",
              "inputPinExts": "_78_",
              "_outputPins": "_79_",
              "outputPins": "_80_",
              "text": "_81_",
              "outputPinsInModel": "_82_",
              "outputPinExts": "_83_",
              "editable": "_84_",
              "isFrame": "_85_",
              "frameAry": "_86_",
              "inputJoints": "_87_",
              "outputJoints": "_88_",
              "ellipsis": "_89_",
              "geo": "_90_",
              "asMapArea": "_91_",
              "borderColor": "_92_",
              "borderWidth": "_93_",
              "borderStyle": "_94_",
              "borderRadius": "_95_",
              "backgroundColor": "_96_",
              "background": "_97_",
              "evtType": "_98_",
              "click": "_99_",
              "diagramAry": "_100_",
              "commentAry": "_101_",
              "visible": "_102_",
              "_title": "_103_",
              "createTime": "_104_",
              "isGlobal": "_105_",
              "showIO": "_106_",
              "updateTime": "_107_",
              "startFrom": "_108_",
              "focusModelAry": "_109_",
              "zIndexCur": "_110_",
              "con": "_111_",
              "com": "_112_",
              "notes": "_113_",
              "styleInited": "_114_",
              "showType": "_115_",
              "frame": "_116_",
              "frames": "_117_",
              "curDiagram": "_118_"
            }
          },
          "refs": {
            "1": {},
            "3": {},
            "5": {},
            "7": {},
            "10": {},
            "12": {},
            "16": {},
            "18": {},
            "20": {},
            "22": {},
            "24": {},
            "26": {},
            "28": {},
            "30": {},
            "32": {},
            "34": {},
            "36": {},
            "38": {},
            "40": {},
            "44": {},
            "46": {},
            "48": {},
            "50": {},
            "52": {},
            "54": {},
            "56": {},
            "58": {},
            "62": {},
            "64": {},
            "67": {}
          },
          "def": {
            "_R_": "0"
          }
        }
      },
      "toJson": {
        "-v": "1.0.8",
        "id": "u_llscW",
        "title": "主场景",
        "deps": [
          {
            "namespace": "mybricks.ktaro.swiper",
            "version": "1.0.0"
          },
          {
            "namespace": "mybricks.ktaro.text",
            "version": "1.0.0"
          },
          {
            "namespace": "mybricks.ktaro.button",
            "version": "1.0.14"
          }
        ],
        "coms": {
          "u_YxhTF": {
            "def": {
              "namespace": "mybricks.ktaro.swiper",
              "version": "1.0.0"
            },
            "title": "轮播",
            "model": {
              "data": {
                "items": [],
                "swiperStyle": {},
                "swiperItemStyle": {},
                "style": {
                  "lineHeight": "14px",
                  "letterSpacing": "0px",
                  "fontSize": "14px",
                  "fontWeight": 400,
                  "color": "#222222",
                  "fontStyle": "normal",
                  "fontFamily": "",
                  "styleEditorUnfold": true
                }
              },
              "inputAry": [],
              "outputAry": [],
              "outputEvents": {
                "onClick": [
                  {
                    "type": "defined",
                    "options": {},
                    "active": true
                  }
                ]
              },
              "style": {
                "display": "block",
                "width": "100%",
                "height": 114,
                "marginTop": 12,
                "marginBottom": 12,
                "marginLeft": 12,
                "marginRight": 12
              }
            },
            "configs": [],
            "inputs": [
              "value",
              "show",
              "hide",
              "showOrHide"
            ],
            "outputs": [
              "onClick"
            ]
          },
          "u_r43rb": {
            "def": {
              "namespace": "mybricks.ktaro.text",
              "version": "1.0.0"
            },
            "title": "文本",
            "model": {
              "data": {
                "text": "文本内容",
                "style": {
                  "lineHeight": "14px",
                  "letterSpacing": "0px",
                  "fontSize": "14px",
                  "fontWeight": 400,
                  "color": "#222222",
                  "fontStyle": "normal",
                  "fontFamily": "",
                  "styleEditorUnfold": true
                },
                "ellipsis": false
              },
              "inputAry": [],
              "outputAry": [],
              "outputEvents": {
                "onClick": [
                  {
                    "type": "defined",
                    "options": {},
                    "active": true
                  }
                ]
              },
              "style": {
                "display": "block",
                "width": "fit-content"
              }
            },
            "configs": [],
            "inputs": [
              "value",
              "show",
              "hide",
              "showOrHide"
            ],
            "outputs": [
              "onClick"
            ]
          },
          "u_6cV92": {
            "def": {
              "namespace": "mybricks.ktaro.button",
              "version": "1.0.14"
            },
            "title": "按钮",
            "model": {
              "data": {
                "asMapArea": false,
                "style": {
                  "borderColor": "#AAA",
                  "borderWidth": "1px",
                  "borderStyle": "solid",
                  "borderRadius": "10px",
                  "backgroundColor": "#FFF",
                  "background": "url() center top / 100% 100% no-repeat, transparent",
                  "lineHeight": "14px",
                  "letterSpacing": "0px",
                  "fontSize": "14px",
                  "fontWeight": 400,
                  "color": "#222222",
                  "fontStyle": "normal",
                  "fontFamily": "",
                  "styleEditorUnfold": true
                },
                "text": "按钮",
                "evtType": "JUMP"
              },
              "inputAry": [],
              "outputAry": [],
              "outputEvents": {
                "click": [
                  {
                    "type": "defined",
                    "options": {},
                    "active": true
                  }
                ]
              },
              "style": {
                "display": "block",
                "width": 80,
                "height": 50
              }
            },
            "configs": [],
            "inputs": [
              "btnText",
              "btnStyle",
              "show",
              "hide",
              "showOrHide"
            ],
            "outputs": [
              "click"
            ]
          }
        },
        "slot": {
          "id": "u_llscW",
          "title": "主场景",
          "comAry": [
            {
              "id": "u_YxhTF",
              "def": {
                "namespace": "mybricks.ktaro.swiper",
                "version": "1.0.0"
              }
            },
            {
              "id": "u_r43rb",
              "def": {
                "namespace": "mybricks.ktaro.text",
                "version": "1.0.0"
              }
            },
            {
              "id": "u_6cV92",
              "def": {
                "namespace": "mybricks.ktaro.button",
                "version": "1.0.14"
              }
            }
          ],
          "style": {
            "zoom": 1,
            "width": 375,
            "height": 667,
            "layout": "flex-column",
            "justifyContent": "flex-start",
            "alignItems": "flex-start"
          }
        },
        "comsAutoRun": {},
        "_inputs": [],
        "_outputs": [],
        "inputs": [],
        "outputs": [],
        "cons": {},
        "pinRels": {},
        "pinProxies": {},
        "plugins": {},
        "configuration": {
          "domainFileMap": {
            "baseFileId": 431
          }
        }
      },
      "pageConfig": {
        "pagePath": "pages/bbb/index"
      }
    }
  },
  {
    "fileInfo": {
      "id": 218,
      "name": "列表页面",
      "extName": "mp-page"
    },
    "fileData": {},
    "text": "标签项",
    "selectedIconPath": "https://ali-ec.static.yximgs.com/udata/pkg/eshop/chrome-plugin-upload/2023-03-15/1678869092382.c95d52033e4fb365.png",
    "selectedIconStyle": {
      "width": "32px",
      "height": "32px"
    },
    "selectedTextStyle": {
      "lineHeight": "14px",
      "letterSpacing": "0px",
      "fontSize": "14px",
      "fontWeight": 400,
      "color": "#222222",
      "fontStyle": "normal",
      "fontFamily": "",
      "styleEditorUnfold": true
    },
    "normalIconPath": "https://ali-ec.static.yximgs.com/udata/pkg/eshop/chrome-plugin-upload/2023-03-15/1678869110750.f5cf009cd90a320b.png",
    "normalIconStyle": {
      "width": "32px",
      "height": "32px"
    },
    "normalTextStyle": {
      "lineHeight": "14px",
      "letterSpacing": "0px",
      "fontSize": "14px",
      "fontWeight": 400,
      "color": "#222222",
      "fontStyle": "normal",
      "fontFamily": "",
      "styleEditorUnfold": true
    },
    "fileToJson": {
      "content": {
        "xg.desn.stageview": {
          "D": {
            "C": [
              "xg.desn.sdk.ModelState",
              "xg.desn.designer.stageview.ViewSlotModel",
              "xg.desn.designer.stageview.geo.SlotStyleModel",
              "xg.desn.sdk.ComStyle",
              "xg.desn.designer.stageview.topl.PinModel",
              "xg.desn.designer.stageview.geo.GeoComModel",
              "xg.desn.sdk.ComRuntimeModel",
              "xg.desn.designer.stageview.topl.ToplComModel",
              "xg.desn.designer.stageview.topl.DiagramModel",
              "xg.desn.designer.stageview.topl.FrameModel",
              "xg.desn.designer.stageview.geo.SlotModel",
              "xg.desn.designer.stageview.geo.GeoViewModel",
              "xg.desn.designer.stageview.topl.ToplViewModel",
              "xg.desn.designer.stageview.StageViewModel"
            ],
            "W": {
              "id": "_0_",
              "state": "_1_",
              "designerVersion": "_2_",
              "pluginDataset": "_3_",
              "@mybricks/plugins/sql-connector": "_4_",
              "connectors": "_5_",
              "envVars": "_6_",
              "_themes": "_7_",
              "viewSlots": "_8_",
              "top": "_9_",
              "closeable": "_10_",
              "status": "_11_",
              "tabs": "_12_",
              "showTitleBar": "_13_",
              "_height": "_14_",
              "height": "_15_",
              "bottom": "_16_",
              "editViewWidth": "_17_",
              "mainModule": "_18_",
              "instId": "_19_",
              "title": "_20_",
              "slot": "_21_",
              "name": "_22_",
              "style": "_23_",
              "zoom": "_24_",
              "layout": "_25_",
              "justifyContent": "_26_",
              "alignItems": "_27_",
              "width": "_28_",
              "left": "_29_",
              "slots": "_30_",
              "comAry": "_31_",
              "init": "_32_",
              "runtime": "_33_",
              "model": "_34_",
              "data": "_35_",
              "text": "_36_",
              "lineHeight": "_37_",
              "letterSpacing": "_38_",
              "fontSize": "_39_",
              "fontWeight": "_40_",
              "color": "_41_",
              "fontStyle": "_42_",
              "fontFamily": "_43_",
              "styleEditorUnfold": "_44_",
              "ellipsis": "_45_",
              "inputAry": "_46_",
              "outputAry": "_47_",
              "outputEvents": "_48_",
              "onClick": "_49_",
              "type": "_50_",
              "options": "_51_",
              "active": "_52_",
              "display": "_53_",
              "visibleOnce": "_54_",
              "refId": "_55_",
              "def": "_56_",
              "namespace": "_57_",
              "version": "_58_",
              "_autoRun": "_59_",
              "topl": "_60_",
              "_type": "_61_",
              "foldedStyle": "_62_",
              "configPins": "_63_",
              "_inputPins": "_64_",
              "inputPins": "_65_",
              "zIndex": "_66_",
              "deletable": "_67_",
              "conAry": "_68_",
              "direction": "_69_",
              "hostId": "_70_",
              "_schema": "_71_",
              "parent": "_72_",
              "schema": "_73_",
              "inputPinsInModel": "_74_",
              "inputPinExts": "_75_",
              "_outputPins": "_76_",
              "outputPins": "_77_",
              "items": "_78_",
              "outputPinsInModel": "_79_",
              "outputPinExts": "_80_",
              "editable": "_81_",
              "isFrame": "_82_",
              "frameAry": "_83_",
              "inputJoints": "_84_",
              "outputJoints": "_85_",
              "geo": "_86_",
              "diagramAry": "_87_",
              "commentAry": "_88_",
              "visible": "_89_",
              "_title": "_90_",
              "createTime": "_91_",
              "isGlobal": "_92_",
              "showIO": "_93_",
              "updateTime": "_94_",
              "startFrom": "_95_",
              "focusModelAry": "_96_",
              "zIndexCur": "_97_",
              "con": "_98_",
              "com": "_99_",
              "notes": "_100_",
              "styleInited": "_101_",
              "showType": "_102_",
              "frame": "_103_",
              "frames": "_104_",
              "curDiagram": "_105_"
            }
          },
          "refs": {
            "1": {},
            "3": {},
            "5": {},
            "7": {},
            "10": {},
            "12": {},
            "16": {},
            "18": {},
            "20": {},
            "22": {},
            "24": {},
            "26": {},
            "28": {},
            "30": {},
            "32": {},
            "34": {},
            "36": {},
            "38": {},
            "40": {},
            "44": {},
            "46": {},
            "48": {},
            "50": {},
            "52": {},
            "54": {},
            "56": {},
            "60": {},
            "62": {},
            "64": {},
            "66": {},
            "68": {},
            "70": {},
            "72": {},
            "76": {},
            "78": {},
            "81": {}
          },
          "def": {
            "_R_": "0"
          }
        }
      },
      "toJson": {
        "-v": "1.0.8",
        "id": "u_Ysmxa",
        "title": "主场景",
        "deps": [
          {
            "namespace": "mybricks.ktaro.text",
            "version": "1.0.0"
          }
        ],
        "coms": {
          "u_n_e1t": {
            "def": {
              "namespace": "mybricks.ktaro.text",
              "version": "1.0.0"
            },
            "title": "文本",
            "model": {
              "data": {
                "text": "文本内容",
                "style": {
                  "lineHeight": "14px",
                  "letterSpacing": "0px",
                  "fontSize": "14px",
                  "fontWeight": 400,
                  "color": "#222222",
                  "fontStyle": "normal",
                  "fontFamily": "",
                  "styleEditorUnfold": true
                },
                "ellipsis": false
              },
              "inputAry": [],
              "outputAry": [],
              "outputEvents": {
                "onClick": [
                  {
                    "type": "defined",
                    "options": {},
                    "active": true
                  }
                ]
              },
              "style": {
                "display": "block",
                "width": "100%"
              }
            },
            "configs": [],
            "inputs": [
              "value",
              "show",
              "hide",
              "showOrHide"
            ],
            "outputs": [
              "onClick"
            ]
          },
          "u_fS7lp": {
            "def": {
              "namespace": "mybricks.ktaro.text",
              "version": "1.0.0"
            },
            "title": "文本1",
            "model": {
              "data": {
                "text": "文本内容",
                "style": {
                  "lineHeight": "14px",
                  "letterSpacing": "0px",
                  "fontSize": "14px",
                  "fontWeight": 400,
                  "color": "#222222",
                  "fontStyle": "normal",
                  "fontFamily": "",
                  "styleEditorUnfold": true
                },
                "ellipsis": false
              },
              "inputAry": [],
              "outputAry": [],
              "outputEvents": {
                "onClick": [
                  {
                    "type": "defined",
                    "options": {},
                    "active": true
                  }
                ]
              },
              "style": {
                "display": "block",
                "width": "100%"
              }
            },
            "configs": [],
            "inputs": [
              "value",
              "show",
              "hide",
              "showOrHide"
            ],
            "outputs": [
              "onClick"
            ]
          },
          "u_QhKuS": {
            "def": {
              "namespace": "mybricks.ktaro.text",
              "version": "1.0.0"
            },
            "title": "文本2",
            "model": {
              "data": {
                "text": "文本内容",
                "style": {
                  "lineHeight": "14px",
                  "letterSpacing": "0px",
                  "fontSize": "14px",
                  "fontWeight": 400,
                  "color": "#222222",
                  "fontStyle": "normal",
                  "fontFamily": "",
                  "styleEditorUnfold": true
                },
                "ellipsis": false
              },
              "inputAry": [],
              "outputAry": [],
              "outputEvents": {
                "onClick": [
                  {
                    "type": "defined",
                    "options": {},
                    "active": true
                  }
                ]
              },
              "style": {
                "display": "block",
                "width": "100%"
              }
            },
            "configs": [],
            "inputs": [
              "value",
              "show",
              "hide",
              "showOrHide"
            ],
            "outputs": [
              "onClick"
            ]
          },
          "u_sEApK": {
            "def": {
              "namespace": "mybricks.ktaro.text",
              "version": "1.0.0"
            },
            "title": "文本3",
            "model": {
              "data": {
                "text": "文本内容",
                "style": {
                  "lineHeight": "14px",
                  "letterSpacing": "0px",
                  "fontSize": "14px",
                  "fontWeight": 400,
                  "color": "#222222",
                  "fontStyle": "normal",
                  "fontFamily": "",
                  "styleEditorUnfold": true
                },
                "ellipsis": false
              },
              "inputAry": [],
              "outputAry": [],
              "outputEvents": {
                "onClick": [
                  {
                    "type": "defined",
                    "options": {},
                    "active": true
                  }
                ]
              },
              "style": {
                "display": "block",
                "width": "100%"
              }
            },
            "configs": [],
            "inputs": [
              "value",
              "show",
              "hide",
              "showOrHide"
            ],
            "outputs": [
              "onClick"
            ]
          }
        },
        "slot": {
          "id": "u_Ysmxa",
          "title": "主场景",
          "comAry": [
            {
              "id": "u_n_e1t",
              "def": {
                "namespace": "mybricks.ktaro.text",
                "version": "1.0.0"
              }
            },
            {
              "id": "u_fS7lp",
              "def": {
                "namespace": "mybricks.ktaro.text",
                "version": "1.0.0"
              }
            },
            {
              "id": "u_QhKuS",
              "def": {
                "namespace": "mybricks.ktaro.text",
                "version": "1.0.0"
              }
            },
            {
              "id": "u_sEApK",
              "def": {
                "namespace": "mybricks.ktaro.text",
                "version": "1.0.0"
              }
            }
          ],
          "style": {
            "zoom": 1,
            "width": 375,
            "height": 667,
            "layout": "flex-column",
            "justifyContent": "flex-start",
            "alignItems": "flex-start"
          }
        },
        "comsAutoRun": {},
        "_inputs": [],
        "_outputs": [],
        "inputs": [],
        "outputs": [],
        "cons": {},
        "pinRels": {},
        "pinProxies": {},
        "plugins": {},
        "configuration": {
          "domainFileMap": {
            "baseFileId": 430
          }
        }
      },
      "pageConfig": {
        "pagePath": "pages/ccc/index"
      }
    }
  }
]